DeepSearch/DeepSearch.py
DeepSearch/DeepSearchCLI.py
DeepSearch/ModelLoader.py
DeepSearch/__init__.py
DeepSearch/models/InceptionV3.py
DeepSearch/models/ResNet50.py
DeepSearch/models/VGG16.py
DeepSearch/models/Xception.py
DeepSearch/models/__init__.py
DeepSearch/weights/__init__.py
deep_search_engine-0.0.9.dist-info/LICENSE
deep_search_engine-0.0.9.dist-info/METADATA
deep_search_engine-0.0.9.dist-info/WHEEL
deep_search_engine-0.0.9.dist-info/entry_points.txt
deep_search_engine-0.0.9.dist-info/top_level.txt
deep_search_engine-0.0.9.dist-info/RECORD
