Metadata-Version: 2.1
Name: deep-search-engine
Version: 0.0.9
Summary: DeepSearch image search engine
Home-page: https://github.com/martinholecekmax/DeepSearch
Author: Martin Holecek
Author-email: <martin.holecek.max@gmail.com>
License: MIT
Keywords: DeepSearch image search,AI image search,image search engine,deep image search
Classifier: Development Status :: 3 - Alpha
Classifier: Intended Audience :: Developers
Classifier: Topic :: Software Development :: Build Tools
Classifier: License :: OSI Approved :: MIT License
Classifier: Programming Language :: Python :: 3
Classifier: Programming Language :: Python :: 3.10
License-File: LICENSE
Requires-Dist: annoy
Requires-Dist: keras
Requires-Dist: Keras-Preprocessing
Requires-Dist: numpy
Requires-Dist: pandas
Requires-Dist: Pillow
Requires-Dist: tqdm
Requires-Dist: tensorflow
Requires-Dist: typing-extensions
Requires-Dist: Click
